{
  "components": [
    /*
    {
      "type": "CleverStocker.Spider.DebugStockSpider, CleverStocker.Spider",
      "services": [
        {
          "type": "CleverStocker.Services.IStockSpiderService, CleverStocker.Services"
        }
      ],
      "injectProperties": true
    },
    */
    {
      "type": "CleverStocker.Spider.Sina.SinaStockSpider, CleverStocker.Spider.Sina",
      "services": [
        {
          "type": "CleverStocker.Services.IStockSpiderService, CleverStocker.Services"
        }
      ],
      "injectProperties": true
    },
    {
      "type": "CleverStocker.DataAccess.DBContext, CleverStocker.DataAccess",
      "services": [
        {
          "type": "CleverStocker.DataAccess.DBContext, CleverStocker.DataAccess"
        }
      ]
    },
    {
      "type": "CleverStocker.Services.StockService, CleverStocker.Services",
      "services": [
        {
          "type": "CleverStocker.Services.IStockService, CleverStocker.Services"
        }
      ],
      "instanceScope": "single-instance"
    },
    {
      "type": "CleverStocker.Services.QuotaService, CleverStocker.Services",
      "services": [
        {
          "type": "CleverStocker.Services.IQuotaService, CleverStocker.Services"
        }
      ],
      "instanceScope": "single-instance"
    },
    {
      "type": "CleverStocker.Services.CompanyService, CleverStocker.Services",
      "services": [
        {
          "type": "CleverStocker.Services.ICompanyService, CleverStocker.Services"
        }
      ],
      "instanceScope": "single-instance"
    },
    {
      "type": "CleverStocker.Services.MarketQuotaService, CleverStocker.Services",
      "services": [
        {
          "type": "CleverStocker.Services.IMarketQuotaService, CleverStocker.Services"
        }
      ],
      "instanceScope": "single-instance"
    },
    {
      "type": "CleverStocker.Services.RecentQuotaService, CleverStocker.Services",
      "services": [
        {
          "type": "CleverStocker.Services.IRecentQuotaService, CleverStocker.Services"
        }
      ],
      "instanceScope": "single-instance"
    },
    {
      "type": "CleverStocker.Services.TradeService, CleverStocker.Services",
      "services": [
        {
          "type": "CleverStocker.Services.ITradeService, CleverStocker.Services"
        }
      ],
      "instanceScope": "single-instance"
    }
  ]
}